barkMatterPy/Builtins.py
barkMatterPy/BytecodeCaching.py
barkMatterPy/Bytecodes.py
barkMatterPy/CacheCleanup.py
barkMatterPy/Constants.py
barkMatterPy/EncryptedNexia.py
barkMatterPy/Errors.py
barkMatterPy/HardImportRegistry.py
barkMatterPy/MainControl.py
barkMatterPy/ModuleRegistry.py
barkMatterPy/OptionParsing.py
barkMatterPy/Options.py
barkMatterPy/OutputDirectories.py
barkMatterPy/PostProcessing.py
barkMatterPy/Progress.py
barkMatterPy/PythonFlavors.py
barkMatterPy/PythonOperators.py
barkMatterPy/PythonVersions.py
barkMatterPy/Serialization.py
barkMatterPy/SourceCodeReferences.py
barkMatterPy/Tracing.py
barkMatterPy/TreeXML.py
barkMatterPy/Variables.py
barkMatterPy/Version.py
barkMatterPy/__init__.py
barkMatterPy/__main__.py
barkMatterPy/__past__.py
barkMatterPy/build/DataComposerInterface.py
barkMatterPy/build/SconsCaching.py
barkMatterPy/build/SconsCompilerSettings.py
barkMatterPy/build/SconsHacks.py
barkMatterPy/build/SconsInterface.py
barkMatterPy/build/SconsProgress.py
barkMatterPy/build/SconsSpawn.py
barkMatterPy/build/SconsUtils.py
barkMatterPy/build/__init__.py
barkMatterPy/build/inline_copy/appdirs/appdirs.py
barkMatterPy/build/inline_copy/bin/scons.py
barkMatterPy/build/inline_copy/glob2/glob2/__init__.py
barkMatterPy/build/inline_copy/glob2/glob2/compat.py
barkMatterPy/build/inline_copy/glob2/glob2/fnmatch.py
barkMatterPy/build/inline_copy/glob2/glob2/impl.py
barkMatterPy/build/inline_copy/jinja2/jinja2/__init__.py
barkMatterPy/build/inline_copy/jinja2/jinja2/_compat.py
barkMatterPy/build/inline_copy/jinja2/jinja2/_identifier.py
barkMatterPy/build/inline_copy/jinja2/jinja2/bccache.py
barkMatterPy/build/inline_copy/jinja2/jinja2/compiler.py
barkMatterPy/build/inline_copy/jinja2/jinja2/constants.py
barkMatterPy/build/inline_copy/jinja2/jinja2/debug.py
barkMatterPy/build/inline_copy/jinja2/jinja2/defaults.py
barkMatterPy/build/inline_copy/jinja2/jinja2/environment.py
barkMatterPy/build/inline_copy/jinja2/jinja2/exceptions.py
barkmatterpy-0.1.1.dist-info/METADATA
barkmatterpy-0.1.1.dist-info/WHEEL
barkmatterpy-0.1.1.dist-info/entry_points.txt
barkmatterpy-0.1.1.dist-info/top_level.txt
barkmatterpy-0.1.1.dist-info/RECORD
