Metadata-Version: 2.4
Name: barkMatterPy
Version: 0.1.1
Summary: barkMatterPy compiler / obfuscation engine
Author-email: JACKMB <gskksksj@gmail.com>
License: MIT
Classifier: Programming Language :: Python :: 3
Classifier: License :: OSI Approved :: MIT License
Classifier: Operating System :: OS Independent
Requires-Python: >=3.8
